scheduler_calendar_utils/__init__.py
scheduler_calendar_utils/helpers.cpython-311-darwin.so
scheduler_calendar_utils/helpers.py
scheduler_calendar_utils-0.5.0.dist-info/METADATA
scheduler_calendar_utils-0.5.0.dist-info/WHEEL
scheduler_calendar_utils-0.5.0.dist-info/top_level.txt
scheduler_calendar_utils-0.5.0.dist-info/RECORD
