Metadata-Version: 2.4
Name: scheduler_calendar_utils
Version: 0.5.0
Summary: Utilities for database/firestore interaction, structured HTTP responses and standardized log messages
Author: Rohaan Nadeem
Requires-Dist: Flask<4,>=3
Requires-Dist: SQLAlchemy<3,>=2
Requires-Dist: Cython<4,>=3
Requires-Dist: PyMySQL<2,>=1
Requires-Dist: cloud-sql-python-connector<2,>=1
Requires-Dist: google-cloud-firestore<3,>=2
Dynamic: author
Dynamic: requires-dist
Dynamic: summary
